Workbook

Sheet Jan 2026
B2: Account Balances | D2: Period Start: | E2: ="Jan 28th ~ Feb 27th, " & Dashboard!$F$2 -> Jan 28th ~ Feb 27th, 2026
B4: Category | C4: Budget | D4: Net Change | E4: Remaining
B5: Essentials | C5: {=Dashboard!E7:E10} -> 0 | D5: =SUMIF(D$12:D998, B5, E$12:E998) + SUMIF(I$12:I998, B5, J$12:J998) -> 0 | E5: =C5+D5 -> 0
B6: Growth | C6: 0 | D6: =SUMIF(D$12:D999, B6, E$12:E999) + SUMIF(I$12:I999, B6, J$12:J999) -> 0 | E6: =C6+D6 -> 0
B7: Stability | C7: 2436 | D7: =SUMIF(D$12:D1000, B7, E$12:E1000) + SUMIF(I$12:I1000, B7, J$12:J1000) -> 0 | E7: =C7+D7 -> 2436
B8: Rewards | C8: 0 | D8: =SUMIF(D$12:D1001, B8, E$12:E1001) + SUMIF(I$12:I1001, B8, J$12:J1001) -> 0 | E8: =C8+D8 -> 0
B11: Date | C11: Description | D11: Category | E11: Amount | G11: Due Date | H11: Payment Name | I11: Category | J11: Amount
B12: =IF(COUNTA(C12:E12)>0, TODAY(), "") | G12: =IFERROR(__xludf.DUMMYFUNCTION("IFERROR(FILTER({DATE(2026, 1, 'Recurring Payments'!$E$5:$E998), 'Recurring Payments'!$B$5:$B998, 'Recurring Payments'!$D$5:$D998, 'Recurring Payments'!$C$5:$C998}, 'Recurring Payments'!$B$5:$B998 <> """", ISNUMBER('Recurring Payments'!$E$5:$E998), (ISBLAN"&"K('Recurring Payments'!$F$5:$F998)) + (EOMONTH(DATE(2026, 1, 1), 0) >= 'Recurring Payments'!$F$5:$F998)), """")"),"")
B13: =IF(COUNTA(C13:E13)>0, TODAY(), "")
B14: =IF(COUNTA(C14:E14)>0, TODAY(), "")
B15: =IF(COUNTA(C15:E15)>0, TODAY(), "")
B16: =IF(COUNTA(C16:E16)>0, TODAY(), "")
B17: =IF(COUNTA(C17:E17)>0, TODAY(), "")
B18: =IF(COUNTA(C18:E18)>0, TODAY(), "")
B19: =IF(COUNTA(C19:E19)>0, TODAY(), "")
B20: =IF(COUNTA(C20:E20)>0, TODAY(), "")
B21: =IF(COUNTA(C21:E21)>0, TODAY(), "")
B22: =IF(COUNTA(C22:E22)>0, TODAY(), "")
B23: =IF(COUNTA(C23:E23)>0, TODAY(), "")
B24: =IF(COUNTA(C24:E24)>0, TODAY(), "")
... B48: =IF(COUNTA(C48:E48)>0, TODAY(), "")

Sheet Recurring Payments
B2: Recurring Payments
B4: Payment Name | C4: Amount | D4: Budget Category | E4: Due Date (Day) | F4: Start Date
B5: Spotify | C5: -9.5 | D5: Essentials | E5: 14 | F5: 46187
B6: Xbox Game Pass | C6: -20 | D6: Essentials | E6: 19 | F6: 46192

Sheet Feb 2026
B2: Account Balances | D2: Period Start: | E2: ="Feb 28th ~ Mar 27th, " & Dashboard!$F$2 -> Feb 28th ~ Mar 27th, 2026
B4: Category | C4: Budget | D4: Net Change | E4: Remaining
B5: Essentials | C5: {='Jan 2026'!E5:E8} -> 0 | D5: =SUMIF(D$12:D999, B5, E$12:E999) + SUMIF(I$12:I999, B5, J$12:J999) -> 0 | E5: =C5+D5 -> 0
B6: Growth | C6: 0 | D6: =SUMIF(D$12:D1000, B6, E$12:E1000) + SUMIF(I$12:I1000, B6, J$12:J1000) -> 0 | E6: =C6+D6 -> 0
B7: Stability | C7: 2436 | D7: =SUMIF(D$12:D1001, B7, E$12:E1001) + SUMIF(I$12:I1001, B7, J$12:J1001) -> 0 | E7: =C7+D7 -> 2436
B8: Rewards | C8: 0 | D8: =SUMIF(D$12:D1002, B8, E$12:E1002) + SUMIF(I$12:I1002, B8, J$12:J1002) -> 0 | E8: =C8+D8 -> 0
B11: Date | C11: Description | D11: Category | E11: Amount | G11: Due Date | H11: Payment Name | I11: Category | J11: Amount
B12: =IF(COUNTA(C12:E12)>0, TODAY(), "") | G12: =IFERROR(__xludf.DUMMYFUNCTION("IFERROR(FILTER({DATE(2026, 2, 'Recurring Payments'!$E$5:$E999), 'Recurring Payments'!$B$5:$B999, 'Recurring Payments'!$D$5:$D999, 'Recurring Payments'!$C$5:$C999}, 'Recurring Payments'!$B$5:$B999 <> """", ISNUMBER('Recurring Payments'!$E$5:$E999), (ISBLAN"&"K('Recurring Payments'!$F$5:$F999)) + (EOMONTH(DATE(2026, 2, 1), 0) >= 'Recurring Payments'!$F$5:$F999)), """")"),"")
B13: =IF(COUNTA(C13:E13)>0, TODAY(), "")
B14: =IF(COUNTA(C14:E14)>0, TODAY(), "")
B15: =IF(COUNTA(C15:E15)>0, TODAY(), "")
B16: =IF(COUNTA(C16:E16)>0, TODAY(), "")
B17: =IF(COUNTA(C17:E17)>0, TODAY(), "")
B18: =IF(COUNTA(C18:E18)>0, TODAY(), "")
B19: =IF(COUNTA(C19:E19)>0, TODAY(), "")
B20: =IF(COUNTA(C20:E20)>0, TODAY(), "")
B21: =IF(COUNTA(C21:E21)>0, TODAY(), "")
B22: =IF(COUNTA(C22:E22)>0, TODAY(), "")
B23: =IF(COUNTA(C23:E23)>0, TODAY(), "")
B24: =IF(COUNTA(C24:E24)>0, TODAY(), "")
... B49: =IF(COUNTA(C49:E49)>0, TODAY(), "")

Sheet Mar 2026
B2: Account Balances | D2: Period Start: | E2: ="Mar 28th ~ Apr 27th, " & Dashboard!$F$2 -> Mar 28th ~ Apr 27th, 2026
B4: Category | C4: Budget | D4: Net Change | E4: Remaining
B5: Essentials | C5: {='Feb 2026'!E5:E8} -> 0 | D5: =SUMIF(D$12:D999, B5, E$12:E999) + SUMIF(I$12:I999, B5, J$12:J999) -> 0 | E5: =C5+D5 -> 0
B6: Growth | C6: 0 | D6: =SUMIF(D$12:D1000, B6, E$12:E1000) + SUMIF(I$12:I1000, B6, J$12:J1000) -> 0 | E6: =C6+D6 -> 0
B7: Stability | C7: 2436 | D7: =SUMIF(D$12:D1001, B7, E$12:E1001) + SUMIF(I$12:I1001, B7, J$12:J1001) -> 0 | E7: =C7+D7 -> 2436
B8: Rewards | C8: 0 | D8: =SUMIF(D$12:D1002, B8, E$12:E1002) + SUMIF(I$12:I1002, B8, J$12:J1002) -> 0 | E8: =C8+D8 -> 0
B11: Date | C11: Description | D11: Category | E11: Amount | G11: Due Date | H11: Payment Name | I11: Category | J11: Amount
B12: =IF(COUNTA(C12:E12)>0, TODAY(), "") | G12: =IFERROR(__xludf.DUMMYFUNCTION("IFERROR(FILTER({DATE(2026, 3, 'Recurring Payments'!$E$5:$E999), 'Recurring Payments'!$B$5:$B999, 'Recurring Payments'!$D$5:$D999, 'Recurring Payments'!$C$5:$C999}, 'Recurring Payments'!$B$5:$B999 <> """", ISNUMBER('Recurring Payments'!$E$5:$E999), (ISBLAN"&"K('Recurring Payments'!$F$5:$F999)) + (EOMONTH(DATE(2026, 3, 1), 0) >= 'Recurring Payments'!$F$5:$F999)), """")"),"")
B13: =IF(COUNTA(C13:E13)>0, TODAY(), "")
B14: =IF(COUNTA(C14:E14)>0, TODAY(), "")
B15: =IF(COUNTA(C15:E15)>0, TODAY(), "")
B16: =IF(COUNTA(C16:E16)>0, TODAY(), "")
B17: =IF(COUNTA(C17:E17)>0, TODAY(), "")
B18: =IF(COUNTA(C18:E18)>0, TODAY(), "")
B19: =IF(COUNTA(C19:E19)>0, TODAY(), "")
B20: =IF(COUNTA(C20:E20)>0, TODAY(), "")
B21: =IF(COUNTA(C21:E21)>0, TODAY(), "")
B22: =IF(COUNTA(C22:E22)>0, TODAY(), "")
B23: =IF(COUNTA(C23:E23)>0, TODAY(), "")
B24: =IF(COUNTA(C24:E24)>0, TODAY(), "")
... B49: =IF(COUNTA(C49:E49)>0, TODAY(), "")

Sheet Apr 2026
B2: Account Balances | D2: Period Start: | E2: ="Apr 28th ~ May 27th, " & Dashboard!$F$2 -> Apr 28th ~ May 27th, 2026
B4: Category | C4: Budget | D4: Net Change | E4: Remaining
B5: Essentials | C5: {='Mar 2026'!E5:E8} -> 0 | D5: =SUMIF(D$12:D999, B5, E$12:E999) + SUMIF(I$12:I999, B5, J$12:J999) -> 0 | E5: =C5+D5 -> 0
B6: Growth | C6: 0 | D6: =SUMIF(D$12:D1000, B6, E$12:E1000) + SUMIF(I$12:I1000, B6, J$12:J1000) -> 0 | E6: =C6+D6 -> 0
B7: Stability | C7: 2436 | D7: =SUMIF(D$12:D1001, B7, E$12:E1001) + SUMIF(I$12:I1001, B7, J$12:J1001) -> 0 | E7: =C7+D7 -> 2436
B8: Rewards | C8: 0 | D8: =SUMIF(D$12:D1002, B8, E$12:E1002) + SUMIF(I$12:I1002, B8, J$12:J1002) -> 0 | E8: =C8+D8 -> 0
B11: Date | C11: Description | D11: Category | E11: Amount | G11: Due Date | H11: Payment Name | I11: Category | J11: Amount
B12: =IF(COUNTA(C12:E12)>0, TODAY(), "") | G12: =IFERROR(__xludf.DUMMYFUNCTION("IFERROR(FILTER({DATE(2026, 4, 'Recurring Payments'!$E$5:$E999), 'Recurring Payments'!$B$5:$B999, 'Recurring Payments'!$D$5:$D999, 'Recurring Payments'!$C$5:$C999}, 'Recurring Payments'!$B$5:$B999 <> """", ISNUMBER('Recurring Payments'!$E$5:$E999), (ISBLAN"&"K('Recurring Payments'!$F$5:$F999)) + (EOMONTH(DATE(2026, 4, 1), 0) >= 'Recurring Payments'!$F$5:$F999)), """")"),"")
B13: =IF(COUNTA(C13:E13)>0, TODAY(), "")
B14: =IF(COUNTA(C14:E14)>0, TODAY(), "")
B15: =IF(COUNTA(C15:E15)>0, TODAY(), "")
B16: =IF(COUNTA(C16:E16)>0, TODAY(), "")
B17: =IF(COUNTA(C17:E17)>0, TODAY(), "")
B18: =IF(COUNTA(C18:E18)>0, TODAY(), "")
B19: =IF(COUNTA(C19:E19)>0, TODAY(), "")
B20: =IF(COUNTA(C20:E20)>0, TODAY(), "")
B21: =IF(COUNTA(C21:E21)>0, TODAY(), "")
B22: =IF(COUNTA(C22:E22)>0, TODAY(), "")
B23: =IF(COUNTA(C23:E23)>0, TODAY(), "")
B24: =IF(COUNTA(C24:E24)>0, TODAY(), "")
... B49: =IF(COUNTA(C49:E49)>0, TODAY(), "")

Sheet Dashboard
N1: Month | O1: Rewards Balance
B2: 25/50/15/10 Financial Plan | E2: Year: | F2: 2026 | N2: Jan | O2: =IF(1<=MONTH(DATEVALUE($F$3&" 1")), VLOOKUP("Rewards", 'Jan 2026'!$B$5:$E$8, 4, FALSE), NA()) -> 0
E3: Current Month: | F3: Jun | N3: Feb | O3: =IF(2<=MONTH(DATEVALUE($F$3&" 1")), VLOOKUP("Rewards", 'Feb 2026'!$B$5:$E$8, 4, FALSE), NA()) -> 0
B4: Monthly Income | C4: 4000 | E4: Show Balances: | F4: TRUE | N4: Mar | O4: =IF(3<=MONTH(DATEVALUE($F$3&" 1")), VLOOKUP("Rewards", 'Mar 2026'!$B$5:$E$8, 4, FALSE), NA()) -> 0
N5: Apr | O5: =IF(4<=MONTH(DATEVALUE($F$3&" 1")), VLOOKUP("Rewards", 'Apr 2026'!$B$5:$E$8, 4, FALSE), NA()) -> 0
B6: Category | C6: Allocation | D6: Budget | E6: Starting Balance | K6: Category | L6: % Achieved | N6: May | O6: =IF(5<=MONTH(DATEVALUE($F$3&" 1")), VLOOKUP("Rewards", 'May 2026'!$B$5:$E$8, 4, FALSE), NA()) -> 0
B7: Essentials | C7: 0.5 | D7: =$C$4*C7 -> 2000 | E7: =0 -> 0 | K7: Growth | L7: {=IFERROR(VLOOKUP("Growth", INDIRECT("'" & $F$3 & " " & $F$2 & "'!$B$5:$E$8"), 3, FALSE) / $D$8, 0)} -> 0 | N7: Jun | O7: =IF(6<=MONTH(DATEVALUE($F$3&" 1")), VLOOKUP("Rewards", 'Jun 2026'!$B$5:$E$8, 4, FALSE), NA()) -> 0
B8: Growth | C8: 0.25 | D8: =$C$4*C8 -> 1000 | E8: =0 -> 0 | N8: Jul | O8: =IF(7<=MONTH(DATEVALUE($F$3&" 1")), VLOOKUP("Rewards", 'Jul 2026'!$B$5:$E$8, 4, FALSE), NA()) -> #N/A
B9: Stability | C9: 0.15 | D9: =$C$4*C9 -> 600 | E9: =2436 -> 2436 | K9: Category | L9: % Remaining | N9: Aug | O9: =IF(8<=MONTH(DATEVALUE($F$3&" 1")), VLOOKUP("Rewards", 'Aug 2026'!$B$5:$E$8, 4, FALSE), NA()) -> #N/A
B10: Rewards | C10: 0.1 | D10: =$C$4*C10 -> 400 | E10: =0 -> 0 | K10: Essentials | L10: {=IFERROR(VLOOKUP("Essentials", INDIRECT("'" & $F$3 & " " & $F$2 & "'!$B$5:$E$8"), 4, FALSE) / VLOOKUP("Essentials", INDIRECT("'" & $F$3 & " " & $F$2 & "'!$B$5:$E$8"), 2, FALSE), 0)} -> 0 | N10: Sep | O10: =IF(9<=MONTH(DATEVALUE($F$3&" 1")), VLOOKUP("Rewards", 'Sep 2026'!$B$5:$E$8, 4, FALSE), NA()) -> #N/A
N11: Oct | O11: =IF(10<=MONTH(DATEVALUE($F$3&" 1")), VLOOKUP("Rewards", 'Oct 2026'!$B$5:$E$8, 4, FALSE), NA()) -> #N/A
D12: Total Balance: | E12: {=SUM(INDIRECT("'" & F3 & " " & F2 & "'!E5"), INDIRECT("'" & F3 & " " & F2 & "'!E7"), INDIRECT("'" & F3 & " " & F2 & "'!E8"))} -> 2406.5 | K12: Category | L12: % Reached | N12: Nov | O12: =IF(11<=MONTH(DATEVALUE($F$3&" 1")), VLOOKUP("Rewards", 'Nov 2026'!$B$5:$E$8, 4, FALSE), NA()) -> #N/A
K13: Stability | L13: {=IFERROR(VLOOKUP("Stability", INDIRECT("'" & $F$3 & " " & $F$2 & "'!$B$5:$E$8"), 4, FALSE) / $E$14, 0)} -> 0.2436 | N13: Dec | O13: =IF(12<=MONTH(DATEVALUE($F$3&" 1")), VLOOKUP("Rewards", 'Dec 2026'!$B$5:$E$8, 4, FALSE), NA()) -> #N/A
D14: Target Stability Fund: | E14: 10000

Sheet May 2026
B2: Account Balances | D2: Period Start: | E2: ="May 28th ~ Jun 27th, " & Dashboard!$F$2 -> May 28th ~ Jun 27th, 2026
B4: Category | C4: Budget | D4: Net Change | E4: Remaining
B5: Essentials | C5: {='Apr 2026'!E5:E8} -> 0 | D5: =SUMIF(D$12:D997, B5, E$12:E997) + SUMIF(I$12:I997, B5, J$12:J997) -> 0 | E5: =C5+D5 -> 0
B6: Growth | C6: 0 | D6: =SUMIF(D$12:D998, B6, E$12:E998) + SUMIF(I$12:I998, B6, J$12:J998) -> 0 | E6: =C6+D6 -> 0
B7: Stability | C7: 2436 | D7: =SUMIF(D$12:D999, B7, E$12:E999) + SUMIF(I$12:I999, B7, J$12:J999) -> 0 | E7: =C7+D7 -> 2436
B8: Rewards | C8: 0 | D8: =SUMIF(D$12:D1000, B8, E$12:E1000) + SUMIF(I$12:I1000, B8, J$12:J1000) -> 0 | E8: =C8+D8 -> 0
B11: Date | C11: Description | D11: Category | E11: Amount | G11: Due Date | H11: Payment Name | I11: Category | J11: Amount
B12: =IF(COUNTA(C12:E12)>0, TODAY(), "") | G12: =IFERROR(__xludf.DUMMYFUNCTION("IFERROR(FILTER({DATE(2026, 5, 'Recurring Payments'!$E$5:$E997), 'Recurring Payments'!$B$5:$B997, 'Recurring Payments'!$D$5:$D997, 'Recurring Payments'!$C$5:$C997}, 'Recurring Payments'!$B$5:$B997 <> """", ISNUMBER('Recurring Payments'!$E$5:$E997), (ISBLAN"&"K('Recurring Payments'!$F$5:$F997)) + (EOMONTH(DATE(2026, 5, 1), 0) >= 'Recurring Payments'!$F$5:$F997)), """")"),"")
B13: =IF(COUNTA(C13:E13)>0, TODAY(), "")
B14: =IF(COUNTA(C14:E14)>0, TODAY(), "")
B15: =IF(COUNTA(C15:E15)>0, TODAY(), "")
B16: =IF(COUNTA(C16:E16)>0, TODAY(), "")
B17: =IF(COUNTA(C17:E17)>0, TODAY(), "")
B18: =IF(COUNTA(C18:E18)>0, TODAY(), "")
B19: =IF(COUNTA(C19:E19)>0, TODAY(), "")
B20: =IF(COUNTA(C20:E20)>0, TODAY(), "")
B21: =IF(COUNTA(C21:E21)>0, TODAY(), "")
B22: =IF(COUNTA(C22:E22)>0, TODAY(), "")
B23: =IF(COUNTA(C23:E23)>0, TODAY(), "")
B24: =IF(COUNTA(C24:E24)>0, TODAY(), "")
... B47: =IF(COUNTA(C47:E47)>0, TODAY(), "")

Sheet Jun 2026
B2: Account Balances | D2: Period Start: | E2: ="Jun 28th ~ Jul 27th, " & Dashboard!$F$2 -> Jun 28th ~ Jul 27th, 2026
B4: Category | C4: Budget | D4: Net Change | E4: Remaining
B5: Essentials | C5: {='May 2026'!E5:E8} -> 0 | D5: =SUMIF(D$12:D999, B5, E$12:E999) + SUMIF(I$12:I999, B5, J$12:J999) -> -29.5 | E5: =C5+D5 -> -29.5
B6: Growth | C6: 0 | D6: =SUMIF(D$12:D1000, B6, E$12:E1000) + SUMIF(I$12:I1000, B6, J$12:J1000) -> 0 | E6: =C6+D6 -> 0
B7: Stability | C7: 2436 | D7: =SUMIF(D$12:D1001, B7, E$12:E1001) + SUMIF(I$12:I1001, B7, J$12:J1001) -> 0 | E7: =C7+D7 -> 2436
B8: Rewards | C8: 0 | D8: =SUMIF(D$12:D1002, B8, E$12:E1002) + SUMIF(I$12:I1002, B8, J$12:J1002) -> 0 | E8: =C8+D8 -> 0
B11: Date | C11: Description | D11: Category | E11: Amount | G11: Due Date | H11: Payment Name | I11: Category | J11: Amount
B12: =IF(COUNTA(C12:E12)>0, TODAY(), "") | G12: =IFERROR(__xludf.DUMMYFUNCTION("IFERROR(FILTER({DATE(2026, 6, 'Recurring Payments'!$E$5:$E999), 'Recurring Payments'!$B$5:$B999, 'Recurring Payments'!$D$5:$D999, 'Recurring Payments'!$C$5:$C999}, 'Recurring Payments'!$B$5:$B999 <> """", ISNUMBER('Recurring Payments'!$E$5:$E999), (ISBLAN"&"K('Recurring Payments'!$F$5:$F999)) + (EOMONTH(DATE(2026, 6, 1), 0) >= 'Recurring Payments'!$F$5:$F999)), """")"),46187.0) -> 46187 | H12: =IFERROR(__xludf.DUMMYFUNCTION("""COMPUTED_VALUE"""),"Spotify") -> Spotify | I12: =IFERROR(__xludf.DUMMYFUNCTION("""COMPUTED_VALUE"""),"Essentials") -> Essentials | J12: =IFERROR(__xludf.DUMMYFUNCTION("""COMPUTED_VALUE"""),-9.5) -> -9.5
B13: =IF(COUNTA(C13:E13)>0, TODAY(), "") | G13: =IFERROR(__xludf.DUMMYFUNCTION("""COMPUTED_VALUE"""),46192.0) -> 46192 | H13: =IFERROR(__xludf.DUMMYFUNCTION("""COMPUTED_VALUE"""),"Xbox Game Pass") -> Xbox Game Pass | I13: =IFERROR(__xludf.DUMMYFUNCTION("""COMPUTED_VALUE"""),"Essentials") -> Essentials | J13: =IFERROR(__xludf.DUMMYFUNCTION("""COMPUTED_VALUE"""),-20.0) -> -20
B14: =IF(COUNTA(C14:E14)>0, TODAY(), "")
B15: =IF(COUNTA(C15:E15)>0, TODAY(), "")
B16: =IF(COUNTA(C16:E16)>0, TODAY(), "")
B17: =IF(COUNTA(C17:E17)>0, TODAY(), "")
B18: =IF(COUNTA(C18:E18)>0, TODAY(), "")
B19: =IF(COUNTA(C19:E19)>0, TODAY(), "")
B20: =IF(COUNTA(C20:E20)>0, TODAY(), "")
B21: =IF(COUNTA(C21:E21)>0, TODAY(), "")
B22: =IF(COUNTA(C22:E22)>0, TODAY(), "")
B23: =IF(COUNTA(C23:E23)>0, TODAY(), "")
B24: =IF(COUNTA(C24:E24)>0, TODAY(), "")
B25: =IF(COUNTA(C25:E25)>0, TODAY(), "")
... B49: =IF(COUNTA(C49:E49)>0, TODAY(), "")

Sheet Jul 2026
B2: Account Balances | D2: Period Start: | E2: ="Jul 28th ~ Aug 27th, " & Dashboard!$F$2 -> Jul 28th ~ Aug 27th, 2026
B4: Category | C4: Budget | D4: Net Change | E4: Remaining
B5: Essentials | C5: {='Jun 2026'!E5:E8} -> -29.5 | D5: =SUMIF(D$12:D998, B5, E$12:E998) + SUMIF(I$12:I998, B5, J$12:J998) -> -29.5 | E5: =C5+D5 -> -59
B6: Growth | C6: 0 | D6: =SUMIF(D$12:D999, B6, E$12:E999) + SUMIF(I$12:I999, B6, J$12:J999) -> 0 | E6: =C6+D6 -> 0
B7: Stability | C7: 2436 | D7: =SUMIF(D$12:D1000, B7, E$12:E1000) + SUMIF(I$12:I1000, B7, J$12:J1000) -> 0 | E7: =C7+D7 -> 2436
B8: Rewards | C8: 0 | D8: =SUMIF(D$12:D1001, B8, E$12:E1001) + SUMIF(I$12:I1001, B8, J$12:J1001) -> 0 | E8: =C8+D8 -> 0
B11: Date | C11: Description | D11: Category | E11: Amount | G11: Due Date | H11: Payment Name | I11: Category | J11: Amount
B12: =IF(COUNTA(C12:E12)>0, TODAY(), "") | G12: =IFERROR(__xludf.DUMMYFUNCTION("IFERROR(FILTER({DATE(2026, 7, 'Recurring Payments'!$E$5:$E998), 'Recurring Payments'!$B$5:$B998, 'Recurring Payments'!$D$5:$D998, 'Recurring Payments'!$C$5:$C998}, 'Recurring Payments'!$B$5:$B998 <> """", ISNUMBER('Recurring Payments'!$E$5:$E998), (ISBLAN"&"K('Recurring Payments'!$F$5:$F998)) + (EOMONTH(DATE(2026, 7, 1), 0) >= 'Recurring Payments'!$F$5:$F998)), """")"),46217.0) -> 46217 | H12: =IFERROR(__xludf.DUMMYFUNCTION("""COMPUTED_VALUE"""),"Spotify") -> Spotify | I12: =IFERROR(__xludf.DUMMYFUNCTION("""COMPUTED_VALUE"""),"Essentials") -> Essentials | J12: =IFERROR(__xludf.DUMMYFUNCTION("""COMPUTED_VALUE"""),-9.5) -> -9.5
B13: =IF(COUNTA(C13:E13)>0, TODAY(), "") | G13: =IFERROR(__xludf.DUMMYFUNCTION("""COMPUTED_VALUE"""),46222.0) -> 46222 | H13: =IFERROR(__xludf.DUMMYFUNCTION("""COMPUTED_VALUE"""),"Xbox Game Pass") -> Xbox Game Pass | I13: =IFERROR(__xludf.DUMMYFUNCTION("""COMPUTED_VALUE"""),"Essentials") -> Essentials | J13: =IFERROR(__xludf.DUMMYFUNCTION("""COMPUTED_VALUE"""),-20.0) -> -20
B14: =IF(COUNTA(C14:E14)>0, TODAY(), "")
B15: =IF(COUNTA(C15:E15)>0, TODAY(), "")
B16: =IF(COUNTA(C16:E16)>0, TODAY(), "")
B17: =IF(COUNTA(C17:E17)>0, TODAY(), "")
B18: =IF(COUNTA(C18:E18)>0, TODAY(), "")
B19: =IF(COUNTA(C19:E19)>0, TODAY(), "")
B20: =IF(COUNTA(C20:E20)>0, TODAY(), "")
B21: =IF(COUNTA(C21:E21)>0, TODAY(), "")
B22: =IF(COUNTA(C22:E22)>0, TODAY(), "")
B23: =IF(COUNTA(C23:E23)>0, TODAY(), "")
B24: =IF(COUNTA(C24:E24)>0, TODAY(), "")
B25: =IF(COUNTA(C25:E25)>0, TODAY(), "")
... B48: =IF(COUNTA(C48:E48)>0, TODAY(), "")

Sheet Aug 2026
B2: Account Balances | D2: Period Start: | E2: ="Aug 28th ~ Sep 27th, " & Dashboard!$F$2 -> Aug 28th ~ Sep 27th, 2026
B4: Category | C4: Budget | D4: Net Change | E4: Remaining
B5: Essentials | C5: {='Jul 2026'!E5:E8} -> -59 | D5: =SUMIF(D$12:D999, B5, E$12:E999) + SUMIF(I$12:I999, B5, J$12:J999) -> -29.5 | E5: =C5+D5 -> -88.5
B6: Growth | C6: 0 | D6: =SUMIF(D$12:D1000, B6, E$12:E1000) + SUMIF(I$12:I1000, B6, J$12:J1000) -> 0 | E6: =C6+D6 -> 0
B7: Stability | C7: 2436 | D7: =SUMIF(D$12:D1001, B7, E$12:E1001) + SUMIF(I$12:I1001, B7, J$12:J1001) -> 0 | E7: =C7+D7 -> 2436
B8: Rewards | C8: 0 | D8: =SUMIF(D$12:D1002, B8, E$12:E1002) + SUMIF(I$12:I1002, B8, J$12:J1002) -> 0 | E8: =C8+D8 -> 0
B11: Date | C11: Description | D11: Category | E11: Amount | G11: Due Date | H11: Payment Name | I11: Category | J11: Amount
B12: =IF(COUNTA(C12:E12)>0, TODAY(), "") | G12: =IFERROR(__xludf.DUMMYFUNCTION("IFERROR(FILTER({DATE(2026, 8, 'Recurring Payments'!$E$5:$E999), 'Recurring Payments'!$B$5:$B999, 'Recurring Payments'!$D$5:$D999, 'Recurring Payments'!$C$5:$C999}, 'Recurring Payments'!$B$5:$B999 <> """", ISNUMBER('Recurring Payments'!$E$5:$E999), (ISBLAN"&"K('Recurring Payments'!$F$5:$F999)) + (EOMONTH(DATE(2026, 8, 1), 0) >= 'Recurring Payments'!$F$5:$F999)), """")"),46248.0) -> 46248 | H12: =IFERROR(__xludf.DUMMYFUNCTION("""COMPUTED_VALUE"""),"Spotify") -> Spotify | I12: =IFERROR(__xludf.DUMMYFUNCTION("""COMPUTED_VALUE"""),"Essentials") -> Essentials | J12: =IFERROR(__xludf.DUMMYFUNCTION("""COMPUTED_VALUE"""),-9.5) -> -9.5
B13: =IF(COUNTA(C13:E13)>0, TODAY(), "") | G13: =IFERROR(__xludf.DUMMYFUNCTION("""COMPUTED_VALUE"""),46253.0) -> 46253 | H13: =IFERROR(__xludf.DUMMYFUNCTION("""COMPUTED_VALUE"""),"Xbox Game Pass") -> Xbox Game Pass | I13: =IFERROR(__xludf.DUMMYFUNCTION("""COMPUTED_VALUE"""),"Essentials") -> Essentials | J13: =IFERROR(__xludf.DUMMYFUNCTION("""COMPUTED_VALUE"""),-20.0) -> -20
B14: =IF(COUNTA(C14:E14)>0, TODAY(), "")
B15: =IF(COUNTA(C15:E15)>0, TODAY(), "")
B16: =IF(COUNTA(C16:E16)>0, TODAY(), "")
B17: =IF(COUNTA(C17:E17)>0, TODAY(), "")
B18: =IF(COUNTA(C18:E18)>0, TODAY(), "")
B19: =IF(COUNTA(C19:E19)>0, TODAY(), "")
B20: =IF(COUNTA(C20:E20)>0, TODAY(), "")
B21: =IF(COUNTA(C21:E21)>0, TODAY(), "")
B22: =IF(COUNTA(C22:E22)>0, TODAY(), "")
B23: =IF(COUNTA(C23:E23)>0, TODAY(), "")
B24: =IF(COUNTA(C24:E24)>0, TODAY(), "")
B25: =IF(COUNTA(C25:E25)>0, TODAY(), "")
... B49: =IF(COUNTA(C49:E49)>0, TODAY(), "")

Sheet Sep 2026
B2: Account Balances | D2: Period Start: | E2: ="Sep 28th ~ Oct 27th, " & Dashboard!$F$2 -> Sep 28th ~ Oct 27th, 2026
B4: Category | C4: Budget | D4: Net Change | E4: Remaining
B5: Essentials | C5: {='Aug 2026'!E5:E8} -> -88.5 | D5: =SUMIF(D$12:D999, B5, E$12:E999) + SUMIF(I$12:I999, B5, J$12:J999) -> -29.5 | E5: =C5+D5 -> -118
B6: Growth | C6: 0 | D6: =SUMIF(D$12:D1000, B6, E$12:E1000) + SUMIF(I$12:I1000, B6, J$12:J1000) -> 0 | E6: =C6+D6 -> 0
B7: Stability | C7: 2436 | D7: =SUMIF(D$12:D1001, B7, E$12:E1001) + SUMIF(I$12:I1001, B7, J$12:J1001) -> 0 | E7: =C7+D7 -> 2436
B8: Rewards | C8: 0 | D8: =SUMIF(D$12:D1002, B8, E$12:E1002) + SUMIF(I$12:I1002, B8, J$12:J1002) -> 0 | E8: =C8+D8 -> 0
B11: Date | C11: Description | D11: Category | E11: Amount | G11: Due Date | H11: Payment Name | I11: Category | J11: Amount
B12: =IF(COUNTA(C12:E12)>0, TODAY(), "") | G12: =IFERROR(__xludf.DUMMYFUNCTION("IFERROR(FILTER({DATE(2026, 9, 'Recurring Payments'!$E$5:$E999), 'Recurring Payments'!$B$5:$B999, 'Recurring Payments'!$D$5:$D999, 'Recurring Payments'!$C$5:$C999}, 'Recurring Payments'!$B$5:$B999 <> """", ISNUMBER('Recurring Payments'!$E$5:$E999), (ISBLAN"&"K('Recurring Payments'!$F$5:$F999)) + (EOMONTH(DATE(2026, 9, 1), 0) >= 'Recurring Payments'!$F$5:$F999)), """")"),46279.0) -> 46279 | H12: =IFERROR(__xludf.DUMMYFUNCTION("""COMPUTED_VALUE"""),"Spotify") -> Spotify | I12: =IFERROR(__xludf.DUMMYFUNCTION("""COMPUTED_VALUE"""),"Essentials") -> Essentials | J12: =IFERROR(__xludf.DUMMYFUNCTION("""COMPUTED_VALUE"""),-9.5) -> -9.5
B13: =IF(COUNTA(C13:E13)>0, TODAY(), "") | G13: =IFERROR(__xludf.DUMMYFUNCTION("""COMPUTED_VALUE"""),46284.0) -> 46284 | H13: =IFERROR(__xludf.DUMMYFUNCTION("""COMPUTED_VALUE"""),"Xbox Game Pass") -> Xbox Game Pass | I13: =IFERROR(__xludf.DUMMYFUNCTION("""COMPUTED_VALUE"""),"Essentials") -> Essentials | J13: =IFERROR(__xludf.DUMMYFUNCTION("""COMPUTED_VALUE"""),-20.0) -> -20
B14: =IF(COUNTA(C14:E14)>0, TODAY(), "")
B15: =IF(COUNTA(C15:E15)>0, TODAY(), "")
B16: =IF(COUNTA(C16:E16)>0, TODAY(), "")
B17: =IF(COUNTA(C17:E17)>0, TODAY(), "")
B18: =IF(COUNTA(C18:E18)>0, TODAY(), "")
B19: =IF(COUNTA(C19:E19)>0, TODAY(), "")
B20: =IF(COUNTA(C20:E20)>0, TODAY(), "")
B21: =IF(COUNTA(C21:E21)>0, TODAY(), "")
B22: =IF(COUNTA(C22:E22)>0, TODAY(), "")
B23: =IF(COUNTA(C23:E23)>0, TODAY(), "")
B24: =IF(COUNTA(C24:E24)>0, TODAY(), "")
B25: =IF(COUNTA(C25:E25)>0, TODAY(), "")
... B49: =IF(COUNTA(C49:E49)>0, TODAY(), "")

Sheet Oct 2026
B2: Account Balances | D2: Period Start: | E2: ="Oct 28th ~ Nov 27th, " & Dashboard!$F$2 -> Oct 28th ~ Nov 27th, 2026
B4: Category | C4: Budget | D4: Net Change | E4: Remaining
B5: Essentials | C5: {='Sep 2026'!E5:E8} -> -118 | D5: =SUMIF(D$12:D999, B5, E$12:E999) + SUMIF(I$12:I999, B5, J$12:J999) -> -29.5 | E5: =C5+D5 -> -147.5
B6: Growth | C6: 0 | D6: =SUMIF(D$12:D1000, B6, E$12:E1000) + SUMIF(I$12:I1000, B6, J$12:J1000) -> 0 | E6: =C6+D6 -> 0
B7: Stability | C7: 2436 | D7: =SUMIF(D$12:D1001, B7, E$12:E1001) + SUMIF(I$12:I1001, B7, J$12:J1001) -> 0 | E7: =C7+D7 -> 2436
B8: Rewards | C8: 0 | D8: =SUMIF(D$12:D1002, B8, E$12:E1002) + SUMIF(I$12:I1002, B8, J$12:J1002) -> 0 | E8: =C8+D8 -> 0
B11: Date | C11: Description | D11: Category | E11: Amount | G11: Due Date | H11: Payment Name | I11: Category | J11: Amount
B12: =IF(COUNTA(C12:E12)>0, TODAY(), "") | G12: =IFERROR(__xludf.DUMMYFUNCTION("IFERROR(FILTER({DATE(2026, 10, 'Recurring Payments'!$E$5:$E999), 'Recurring Payments'!$B$5:$B999, 'Recurring Payments'!$D$5:$D999, 'Recurring Payments'!$C$5:$C999}, 'Recurring Payments'!$B$5:$B999 <> """", ISNUMBER('Recurring Payments'!$E$5:$E999), (ISBLA"&"NK('Recurring Payments'!$F$5:$F999)) + (EOMONTH(DATE(2026, 10, 1), 0) >= 'Recurring Payments'!$F$5:$F999)), """")"),46309.0) -> 46309 | H12: =IFERROR(__xludf.DUMMYFUNCTION("""COMPUTED_VALUE"""),"Spotify") -> Spotify | I12: =IFERROR(__xludf.DUMMYFUNCTION("""COMPUTED_VALUE"""),"Essentials") -> Essentials | J12: =IFERROR(__xludf.DUMMYFUNCTION("""COMPUTED_VALUE"""),-9.5) -> -9.5
B13: =IF(COUNTA(C13:E13)>0, TODAY(), "") | G13: =IFERROR(__xludf.DUMMYFUNCTION("""COMPUTED_VALUE"""),46314.0) -> 46314 | H13: =IFERROR(__xludf.DUMMYFUNCTION("""COMPUTED_VALUE"""),"Xbox Game Pass") -> Xbox Game Pass | I13: =IFERROR(__xludf.DUMMYFUNCTION("""COMPUTED_VALUE"""),"Essentials") -> Essentials | J13: =IFERROR(__xludf.DUMMYFUNCTION("""COMPUTED_VALUE"""),-20.0) -> -20
B14: =IF(COUNTA(C14:E14)>0, TODAY(), "")
B15: =IF(COUNTA(C15:E15)>0, TODAY(), "")
B16: =IF(COUNTA(C16:E16)>0, TODAY(), "")
B17: =IF(COUNTA(C17:E17)>0, TODAY(), "")
B18: =IF(COUNTA(C18:E18)>0, TODAY(), "")
B19: =IF(COUNTA(C19:E19)>0, TODAY(), "")
B20: =IF(COUNTA(C20:E20)>0, TODAY(), "")
B21: =IF(COUNTA(C21:E21)>0, TODAY(), "")
B22: =IF(COUNTA(C22:E22)>0, TODAY(), "")
B23: =IF(COUNTA(C23:E23)>0, TODAY(), "")
B24: =IF(COUNTA(C24:E24)>0, TODAY(), "")
B25: =IF(COUNTA(C25:E25)>0, TODAY(), "")
... B49: =IF(COUNTA(C49:E49)>0, TODAY(), "")

Sheet Nov 2026
B2: Account Balances | D2: Period Start: | E2: ="Nov 28th ~ Dec 27th, " & Dashboard!$F$2 -> Nov 28th ~ Dec 27th, 2026
B4: Category | C4: Budget | D4: Net Change | E4: Remaining
B5: Essentials | C5: {='Oct 2026'!E5:E8} -> -147.5 | D5: =SUMIF(D$12:D999, B5, E$12:E999) + SUMIF(I$12:I999, B5, J$12:J999) -> -29.5 | E5: =C5+D5 -> -177
B6: Growth | C6: 0 | D6: =SUMIF(D$12:D1000, B6, E$12:E1000) + SUMIF(I$12:I1000, B6, J$12:J1000) -> 0 | E6: =C6+D6 -> 0
B7: Stability | C7: 2436 | D7: =SUMIF(D$12:D1001, B7, E$12:E1001) + SUMIF(I$12:I1001, B7, J$12:J1001) -> 0 | E7: =C7+D7 -> 2436
B8: Rewards | C8: 0 | D8: =SUMIF(D$12:D1002, B8, E$12:E1002) + SUMIF(I$12:I1002, B8, J$12:J1002) -> 0 | E8: =C8+D8 -> 0
B11: Date | C11: Description | D11: Category | E11: Amount | G11: Due Date | H11: Payment Name | I11: Category | J11: Amount
B12: =IF(COUNTA(C12:E12)>0, TODAY(), "") | G12: =IFERROR(__xludf.DUMMYFUNCTION("IFERROR(FILTER({DATE(2026, 11, 'Recurring Payments'!$E$5:$E999), 'Recurring Payments'!$B$5:$B999, 'Recurring Payments'!$D$5:$D999, 'Recurring Payments'!$C$5:$C999}, 'Recurring Payments'!$B$5:$B999 <> """", ISNUMBER('Recurring Payments'!$E$5:$E999), (ISBLA"&"NK('Recurring Payments'!$F$5:$F999)) + (EOMONTH(DATE(2026, 11, 1), 0) >= 'Recurring Payments'!$F$5:$F999)), """")"),46340.0) -> 46340 | H12: =IFERROR(__xludf.DUMMYFUNCTION("""COMPUTED_VALUE"""),"Spotify") -> Spotify | I12: =IFERROR(__xludf.DUMMYFUNCTION("""COMPUTED_VALUE"""),"Essentials") -> Essentials | J12: =IFERROR(__xludf.DUMMYFUNCTION("""COMPUTED_VALUE"""),-9.5) -> -9.5
B13: =IF(COUNTA(C13:E13)>0, TODAY(), "") | G13: =IFERROR(__xludf.DUMMYFUNCTION("""COMPUTED_VALUE"""),46345.0) -> 46345 | H13: =IFERROR(__xludf.DUMMYFUNCTION("""COMPUTED_VALUE"""),"Xbox Game Pass") -> Xbox Game Pass | I13: =IFERROR(__xludf.DUMMYFUNCTION("""COMPUTED_VALUE"""),"Essentials") -> Essentials | J13: =IFERROR(__xludf.DUMMYFUNCTION("""COMPUTED_VALUE"""),-20.0) -> -20
B14: =IF(COUNTA(C14:E14)>0, TODAY(), "")
B15: =IF(COUNTA(C15:E15)>0, TODAY(), "")
B16: =IF(COUNTA(C16:E16)>0, TODAY(), "")
B17: =IF(COUNTA(C17:E17)>0, TODAY(), "")
B18: =IF(COUNTA(C18:E18)>0, TODAY(), "")
B19: =IF(COUNTA(C19:E19)>0, TODAY(), "")
B20: =IF(COUNTA(C20:E20)>0, TODAY(), "")
B21: =IF(COUNTA(C21:E21)>0, TODAY(), "")
B22: =IF(COUNTA(C22:E22)>0, TODAY(), "")
B23: =IF(COUNTA(C23:E23)>0, TODAY(), "")
B24: =IF(COUNTA(C24:E24)>0, TODAY(), "")
B25: =IF(COUNTA(C25:E25)>0, TODAY(), "")
... B49: =IF(COUNTA(C49:E49)>0, TODAY(), "")

Sheet Dec 2026
B2: Account Balances | D2: Period Start: | E2: ="Dec 28th ~ Jan 27th, " & Dashboard!$F$2 -> Dec 28th ~ Jan 27th, 2026
B4: Category | C4: Budget | D4: Net Change | E4: Remaining
B5: Essentials | C5: {='Nov 2026'!E5:E8} -> -177 | D5: =SUMIF(D$12:D999, B5, E$12:E999) + SUMIF(I$12:I999, B5, J$12:J999) -> -29.5 | E5: =C5+D5 -> -206.5
B6: Growth | C6: 0 | D6: =SUMIF(D$12:D1000, B6, E$12:E1000) + SUMIF(I$12:I1000, B6, J$12:J1000) -> 0 | E6: =C6+D6 -> 0
B7: Stability | C7: 2436 | D7: =SUMIF(D$12:D1001, B7, E$12:E1001) + SUMIF(I$12:I1001, B7, J$12:J1001) -> 0 | E7: =C7+D7 -> 2436
B8: Rewards | C8: 0 | D8: =SUMIF(D$12:D1002, B8, E$12:E1002) + SUMIF(I$12:I1002, B8, J$12:J1002) -> 0 | E8: =C8+D8 -> 0
B11: Date | C11: Description | D11: Category | E11: Amount | G11: Due Date | H11: Payment Name | I11: Category | J11: Amount
B12: =IF(COUNTA(C12:E12)>0, TODAY(), "") | G12: =IFERROR(__xludf.DUMMYFUNCTION("IFERROR(FILTER({DATE(2026, 12, 'Recurring Payments'!$E$5:$E999), 'Recurring Payments'!$B$5:$B999, 'Recurring Payments'!$D$5:$D999, 'Recurring Payments'!$C$5:$C999}, 'Recurring Payments'!$B$5:$B999 <> """", ISNUMBER('Recurring Payments'!$E$5:$E999), (ISBLA"&"NK('Recurring Payments'!$F$5:$F999)) + (EOMONTH(DATE(2026, 12, 1), 0) >= 'Recurring Payments'!$F$5:$F999)), """")"),46370.0) -> 46370 | H12: =IFERROR(__xludf.DUMMYFUNCTION("""COMPUTED_VALUE"""),"Spotify") -> Spotify | I12: =IFERROR(__xludf.DUMMYFUNCTION("""COMPUTED_VALUE"""),"Essentials") -> Essentials | J12: =IFERROR(__xludf.DUMMYFUNCTION("""COMPUTED_VALUE"""),-9.5) -> -9.5
B13: =IF(COUNTA(C13:E13)>0, TODAY(), "") | G13: =IFERROR(__xludf.DUMMYFUNCTION("""COMPUTED_VALUE"""),46375.0) -> 46375 | H13: =IFERROR(__xludf.DUMMYFUNCTION("""COMPUTED_VALUE"""),"Xbox Game Pass") -> Xbox Game Pass | I13: =IFERROR(__xludf.DUMMYFUNCTION("""COMPUTED_VALUE"""),"Essentials") -> Essentials | J13: =IFERROR(__xludf.DUMMYFUNCTION("""COMPUTED_VALUE"""),-20.0) -> -20
B14: =IF(COUNTA(C14:E14)>0, TODAY(), "")
B15: =IF(COUNTA(C15:E15)>0, TODAY(), "")
B16: =IF(COUNTA(C16:E16)>0, TODAY(), "")
B17: =IF(COUNTA(C17:E17)>0, TODAY(), "")
B18: =IF(COUNTA(C18:E18)>0, TODAY(), "")
B19: =IF(COUNTA(C19:E19)>0, TODAY(), "")
B20: =IF(COUNTA(C20:E20)>0, TODAY(), "")
B21: =IF(COUNTA(C21:E21)>0, TODAY(), "")
B22: =IF(COUNTA(C22:E22)>0, TODAY(), "")
B23: =IF(COUNTA(C23:E23)>0, TODAY(), "")
B24: =IF(COUNTA(C24:E24)>0, TODAY(), "")
B25: =IF(COUNTA(C25:E25)>0, TODAY(), "")
... B49: =IF(COUNTA(C49:E49)>0, TODAY(), "")
